README.rst
setup.py
ago/__init__.py
ago/ago.py
ago.egg-info/PKG-INFO
ago.egg-info/SOURCES.txt
ago.egg-info/dependency_links.txt
ago.egg-info/top_level.txt
ago/tests/__init__.py
ago/tests/test_ago.py