Metadata-Version: 2.1
Name: ago
Version: 0.0.95
Summary: ago: Human readable timedeltas
Home-page: https://git.unturf.com/python/ago
Author: Russell Ballestrini
Author-email: russell.ballestrini@gmail.com
License: Public Domain
Keywords: ago human readable time deltas timedelta datetime timestamp
Platform: All
